flask_envs.py
Flask_Envs-0.1.2.dist-info/LICENSE
Flask_Envs-0.1.2.dist-info/METADATA
Flask_Envs-0.1.2.dist-info/WHEEL
Flask_Envs-0.1.2.dist-info/top_level.txt
Flask_Envs-0.1.2.dist-info/RECORD
