Metadata-Version: 2.1
Name: Flask-Envs
Version: 0.1.2
Summary: Environment tools and configuration for Flask applications
Home-page: http://packages.python.org/flask-envs/
Author: Jonathan Lancar
Author-email: jonaphin@gmail.com
License: MIT
Platform: any
Classifier: Development Status :: 4 - Beta
Classifier: Environment :: Web Environment
Classifier: Intended Audience :: Developers
Classifier: License :: OSI Approved :: MIT License
Classifier: Operating System :: OS Independent
Classifier: Programming Language :: Python
Classifier: Topic :: Internet :: WWW/HTTP :: Dynamic Content
Classifier: Topic :: Software Development :: Libraries :: Python Modules
Requires-Dist: Flask
Requires-Dist: pyyaml
